{
  "tenantId": "hr",
  "moduleName": "common-masters",
  "Purpose": [
    {
      "purposeId": 1,
      "name": "residentialPlottedColony",
      "purposeCode": "RPL",
      "caseType_id": 1,
      "description": "Residential",
      "isActive": 1,
      "edcPercentage": 25,
      "idwPercentage": 25,
      "plotTypeId": 1,
      "isDisableForNewEntry": null,
      "disableRemarks": null,
      "scrutinyFeeCharges": {
        "Plotted Commercial": {
          "far": 1.75
        }
      },
      "licenseFeeCharges": {
        "Plotted Commercial": {
          "far": 1.75
        }
      },
      "conversionCharges": {
        "Plotted Commercial": {
          "far": 1.75
        }
      },
      "externalDevelopmentCharges": {
        "Plotted Commercial": {
          "far": 1.75
        }
      },
      "stateInfrastructureDevelopmentCharges": {
        "Plotted Commercial": {
          "far": 1.75
        }
      }
    },
    {
      "purposeId": 2,
      "name": "Commercial License in commercial Zone",
      "purposeCode": "CIC",
      "caseType_id": 1,
      "description": "Commercial",
      "isActive": 1,
      "edcPercentage": 25,
      "idwPercentage": 25,
      "plotTypeId": 2,
      "isDisableForNewEntry": null,
      "disableRemarks": null,
      "scrutinyFeeCharges": "",
      "licenseFeeCharges": "",
      "externalDevelopmentCharges": "",
      "conversionCharges": "",
      "stateInfrastructureDevelopmentCharges": ""
    },
    {
      "purposeId": 5,
      "name": "IT/Cyber Park",
      "purposeCode": "ITP",
      "caseType_id": 1,
      "description": "Cyber Park",
      "isActive": 1,
      "edcPercentage": 25,
      "idwPercentage": 37.5,
      "plotTypeId": 2,
      "isDisableForNewEntry": null,
      "disableRemarks": null,
      "scrutinyFeeCharges": {
        "IT Colony Commercial":{
          "far": 150
        }
      },
      "licenseFeeCharges": {
        "IT Colony Commercial":{
          "far": 150
        }
      },
      "externalDevelopmentCharges": {
        "IT Colony Commercial":{
          "far": 150
        }
      },
      "conversionCharges": {
        "IT Colony Commercial":{
          "far": 150
        }
      },
      "stateInfrastructureDevelopmentCharges": {
        "IT Colony Commercial":{
          "far": 150
        }
      }
    },
    {
      "purposeId": 6,
      "name": "IT/Cyber City",
      "purposeCode": "ITC",
      "caseType_id": 1,
      "description": "Cyber City",
      "isActive": 1,
      "edcPercentage": 25,
      "idwPercentage": 37.5,
      "plotTypeId": 2,
      "isDisableForNewEntry": null,
      "disableRemarks": null,
      "scrutinyFeeCharges": {
        "IT Colony Commercial":{
          "far": 150
        }
      },
      "licenseFeeCharges": {
        "IT Colony Commercial":{
          "far": 150
        }
      },
      "externalDevelopmentCharges": {
        "IT Colony Commercial":{
          "far": 150
        }
      },
      "conversionCharges": {
        "IT Colony Commercial":{
          "far": 150
        }
      },
      "stateInfrastructureDevelopmentCharges": {
        "IT Colony Commercial":{
          "far": 150
        }
      }
    },
    {
      "purposeId": 7,
      "name": "Industrial Plotted colony in Industrial Zone",
      "purposeCode": "IPL",
      "caseType_id": 1,
      "description": "Industrial",
      "isActive": 1,
      "edcPercentage": 25,
      "idwPercentage": 25,
      "plotTypeId": 1,
      "isDisableForNewEntry": null,
      "disableRemarks": null,
      "scrutinyFeeCharges": {
        "Industrial Colony Commercial":{
          "far": 1.50
        }
      },
      "licenseFeeCharges": {
        "Industrial Colony Commercial":{
          "far": 1.50
        }
      },
      "externalDevelopmentCharges": {
        "Industrial Colony Commercial":{
          "far": 1.50
        }      },
      "conversionCharges": {
        "Industrial Colony Commercial":{
          "far": 1.50
        }      },
      "stateInfrastructureDevelopmentCharges": {
        "Industrial Colony Commercial":{
          "far": 1.50
        }      }
    },
    {
      "purposeId": 63,
      "name": "Commercial Licence in residential Zone",
      "purposeCode": "CIR",
      "caseType_id": 1,
      "description": "Commercial",
      "isActive": 1,
      "edcPercentage": 25,
      "idwPercentage": 25,
      "plotTypeId": 2,
      "isDisableForNewEntry": 1,
      "disableRemarks": "",
      "scrutinyFeeCharges": "",
      "licenseFeeCharges": "",
      "externalDevelopmentCharges": "",
      "conversionCharges": "",
      "stateInfrastructureDevelopmentCharges": ""
    },
    {
      "purposeId": 64,
      "name": "Industrial Plotted colony in Agriculture Zone",
      "purposeCode": "IPA",
      "caseType_id": 1,
      "description": "Industrial",
      "isActive": 1,
      "edcPercentage": 25,
      "idwPercentage": 25,
      "plotTypeId": 1,
      "isDisableForNewEntry": null,
      "disableRemarks": null,
      "scrutinyFeeCharges": {
        "Industrial Colony Commercial":{
          "far": 1.50
        }      
      },
      "licenseFeeCharges": {
        "Industrial Colony Commercial":{
          "far": 1.50
        }      
      },
      "externalDevelopmentCharges": {
        "Industrial Colony Commercial":{
          "far": 1.50
        }      
      },
      "conversionCharges": {
        "Industrial Colony Commercial":{
          "far": 1.50
        }      
      },
      "stateInfrastructureDevelopmentCharges": {
        "Industrial Colony Commercial":{
          "far": 1.50
        }      
      }
    },
    {
      "purposeId": 73,
      "name": "Residential GH with minority plotted area",
      "purposeCode": "RGP",
      "caseType_id": 1,
      "description": "Residential GH with minority Plotted area",
      "isActive": 1,
      "edcPercentage": 25,
      "idwPercentage": 25,
      "plotTypeId": 2,
      "isDisableForNewEntry": null,
      "disableRemarks": null,
      "scrutinyFeeCharges": {
        "Group Housing Commercial":{
          "far": 1.75
        }      
      },
      "licenseFeeCharges": {
        "Group Housing Commercial":{
          "far": 1.50
        }      
      },
      "externalDevelopmentCharges": {
        "Group Housing Commercial":{
          "far": 1.50
        }      
      },
      "conversionCharges": {
        "Group Housing Commercial":{
          "far": 1.50
        }      
      },
      "stateInfrastructureDevelopmentCharges": {
        "Group Housing Commercial":{
          "far": 1.50
        }      
      }
    },
    {
      "purposeId": 74,
      "name": "AFFORDABLE HOUSING PROJECT",
      "purposeCode": "AHP",
      "caseType_id": 1,
      "description": "AFFORDABLE HOUSING PROJECT",
      "isActive": 1,
      "edcPercentage": 25,
      "idwPercentage": 25,
      "plotTypeId": 2,
      "isDisableForNewEntry": 1,
      "disableRemarks": null,
      "scrutinyFeeCharges": "",
      "licenseFeeCharges": "",
      "externalDevelopmentCharges": "",
      "conversionCharges": "",
      "stateInfrastructureDevelopmentCharges": ""
    },
    {
      "purposeId": 75,
      "name": "Special Zone GH-cum-comm Project",
      "purposeCode": "SGC",
      "caseType_id": 1,
      "description": "Special Zone GH-cum-comm Project",
      "isActive": 1,
      "edcPercentage": 25,
      "idwPercentage": 25,
      "plotTypeId": 2,
      "isDisableForNewEntry": null,
      "disableRemarks": null,
      "scrutinyFeeCharges":  {
        "Group Housing Commercial":{
          "far": 1.75
        }      
      },
      "licenseFeeCharges": {
        "Group Housing Commercial":{
          "far": 1.50
        }      
      },
      "externalDevelopmentCharges": {
        "Group Housing Commercial":{
          "far": 1.50
        }      
      },
      "conversionCharges": {
        "Group Housing Commercial":{
          "far": 1.50
        }      
      },
      "stateInfrastructureDevelopmentCharges": {
        "Group Housing Commercial":{
          "far": 1.50
        }      
      }
    },
    {
      "purposeId": 78,
      "name": "Commercial in Special Zone",
      "purposeCode": "CIS",
      "caseType_id": 1,
      "description": "Commercial in Special Zone",
      "isActive": 1,
      "edcPercentage": 25,
      "idwPercentage": 25,
      "plotTypeId": 2,
      "isDisableForNewEntry": null,
      "disableRemarks": null,
      "scrutinyFeeCharges": "",
      "licenseFeeCharges": "",
      "externalDevelopmentCharges": "",
      "conversionCharges": "",
      "stateInfrastructureDevelopmentCharges": ""
    },
    {
      "purposeId": 83,
      "name": "Deen Dayal Jan Awas Yojna-Affordable Plotted 2016",
      "purposeCode": "DDJAY-APHP",
      "caseType_id": 1,
      "description": "Deen Dayal Jan Awas Yojna-Affordable Plotted 2016",
      "isActive": 1,
      "edcPercentage": 25,
      "idwPercentage": 25,
      "plotTypeId": 1,
      "isDisableForNewEntry": 0,
      "disableRemarks": "",
      "scrutinyFeeCharges": {
        "DDJAY": {
          "far": 1.75
        }
      },
      "licenseFeeCharges": {
        "DDJAY": {
          "far": 1.75
        }
      },
      "externalDevelopmentCharges": {
        "DDJAY": {
          "far": 1.75
        }
      },
      "conversionCharges": {
        "DDJAY": {
          "far": 1.75
        }
      },
      "stateInfrastructureDevelopmentCharges": {
        "DDJAY": {
          "far": 1.75
        }
      }
    },
    {
      "purposeId": 84,
      "name": "Mixed Land use in Comm Zone with Minority Resi Use",
      "purposeCode": "MLU-CZ",
      "caseType_id": 1,
      "description": "Mixed Land use in Comm Zone with Minority Resi Use",
      "isActive": 1,
      "edcPercentage": 25,
      "idwPercentage": 25,
      "plotTypeId": 2,
      "isDisableForNewEntry": null,
      "disableRemarks": null,
      "scrutinyFeeCharges": "",
      "licenseFeeCharges": "",
      "externalDevelopmentCharges": "",
      "conversionCharges": "",
      "stateInfrastructureDevelopmentCharges": ""
    },
    {
      "purposeId": 85,
      "name": "Mixed Land use in Resi Zone with Minority Comm Use",
      "purposeCode": "MLU-RZ",
      "caseType_id": 1,
      "description": "Mixed Land use in Resi Zone with Minority Comm Use",
      "isActive": 1,
      "edcPercentage": 25,
      "idwPercentage": 25,
      "plotTypeId": 2,
      "isDisableForNewEntry": null,
      "disableRemarks": null,
      "scrutinyFeeCharges": "",
      "licenseFeeCharges": "",
      "externalDevelopmentCharges": "",
      "conversionCharges": "",
      "stateInfrastructureDevelopmentCharges": ""
    },
    {
      "purposeId": 86,
      "name": "New Integrated Licencing Policy (NILP) for Residential",
      "purposeCode": "NILP",
      "caseType_id": 1,
      "description": "New Integrated Licencing Policy (NILP) for Residential",
      "isActive": 1,
      "edcPercentage": 25,
      "idwPercentage": 25,
      "plotTypeId": 2,
      "isDisableForNewEntry": null,
      "disableRemarks": null,
      "scrutinyFeeCharges": "",
      "licenseFeeCharges": "",
      "externalDevelopmentCharges": "",
      "conversionCharges": "",
      "stateInfrastructureDevelopmentCharges": ""
    },
    {
      "purposeId": 87,
      "name": "Low Density Eco-friendly Colony(LDEF)",
      "purposeCode": "LDEF",
      "caseType_id": 1,
      "description": "Low Density Eco-Friendly Colony(LDEF)",
      "isActive": 1,
      "edcPercentage": 25,
      "idwPercentage": 25,
      "plotTypeId": 2,
      "isDisableForNewEntry": null,
      "disableRemarks": null,
      "scrutinyFeeCharges": {
          "Low density Eco friendly": {
              "far": ""
          }
      },
      "licenseFeeCharges": {
        "Low density Eco friendly": {
            "far": ""
        }
    },
      "externalDevelopmentCharges": {
        "Low density Eco friendly": {
            "far": ""
        }
    },
      "conversionCharges": {
        "Low density Eco friendly": {
            "far": ""
        }
    },
      "stateInfrastructureDevelopmentCharges": {
        "Low density Eco friendly": {
            "far": ""
        }
    }
    },
    {
      "purposeId": 89,
      "name": "New Integrated Licensing Policy (NILP) for Commercial",
      "purposeCode": "NILPC",
      "caseType_id": 1,
      "description": "New Integrated Licencing Policy (NILP) for Commercial",
      "isActive": 1,
      "edcPercentage": 25,
      "idwPercentage": 25,
      "plotTypeId": 2,
      "isDisableForNewEntry": null,
      "disableRemarks": null,
      "scrutinyFeeCharges": {
        "NILP":{
          "far": 1.75
        }
      },
      "licenseFeeCharges": {
        "NILP":{
          "far": 1.75
        }      },
      "externalDevelopmentCharges": {
        "NILP":{
          "far": 1.75
        }      },
      "conversionCharges": {
        "NILP":{
          "far": 1.75
        }      },
      "stateInfrastructureDevelopmentCharges": {
        "NILP":{
          "far": 1.75
        }      }
    },
    {
      "purposeId": 90,
      "name": "Transit Oriented Development (TOD)-RGH",
      "purposeCode": "TODGH",
      "caseType_id": 1,
      "description": "Transit Oriented Development (TOD)-RGH",
      "isActive": 1,
      "edcPercentage": 25,
      "idwPercentage": 25,
      "plotTypeId": 2,
      "isDisableForNewEntry": null,
      "disableRemarks": null,
      "scrutinyFeeCharges": {
        "Tod Group Housing":{
          "far": 3.5
        }
      },
      "licenseFeeCharges": {
        "Tod Group Housing":{
          "far": 3.5
        }
      },
      "externalDevelopmentCharges": {
        "Tod Group Housing":{
          "far": 3.5
        }
      },
      "conversionCharges": {
        "Tod Group Housing":{
          "far": 3.5
        }
      },
      "stateInfrastructureDevelopmentCharges": {
        "Tod Group Housing":{
          "far": 3.5
        }
      }
    },
    {
      "purposeId": 91,
      "name": "Transit Oriented Development (TOD)-Comm",
      "purposeCode": "TOD(COMM)",
      "caseType_id": 1,
      "description": "Transit Oriented Development (TOD)-Comm",
      "isActive": 1,
      "edcPercentage": 25,
      "idwPercentage": 25,
      "plotTypeId": 2,
      "isDisableForNewEntry": 0,
      "disableRemarks": "",
      "scrutinyFeeCharges": {
        "Tod Commercial":{
          "far": 3.5
        }
      },
      "licenseFeeCharges": {
        "Tod Commercial":{
          "far": 3.5
        }      },
      "externalDevelopmentCharges": {
        "Tod Commercial":{
          "far": 3.5
        }      },
      "conversionCharges": {
        "Tod Commercial":{
          "far": 3.5
        }      },
      "stateInfrastructureDevelopmentCharges": {
        "Tod Commercial":{
          "far": 3.5
        }      }
    },
    {
      "purposeId": 92,
      "name": "Transit Oriented Development (TOD)-IT",
      "purposeCode": "TODIT",
      "caseType_id": 1,
      "description": "Transit Oriented Development (TOD)-IT",
      "isActive": 1,
      "edcPercentage": 25,
      "idwPercentage": 25,
      "plotTypeId": 2,
      "isDisableForNewEntry": null,
      "disableRemarks": null,
      "scrutinyFeeCharges": {
        "IT Colony Commercial":{
          "far": 150
        }
      },
      "licenseFeeCharges": {
        "IT Colony Commercial":{
          "far": 150
        }      
      },
      "externalDevelopmentCharges": {
        "IT Colony Commercial":{
          "far": 150
        }      
      },
      "conversionCharges": {
        "IT Colony Commercial":{
          "far": 150
        }      
      },
      "stateInfrastructureDevelopmentCharges": {
        "IT Colony Commercial":{
          "far": 150
        }      
      }
    },
    {
      "purposeId": 93,
      "name": "Transit Oriented Development (TOD)-Mix Use Develop",
      "purposeCode": "TODMUD",
      "caseType_id": 1,
      "description": "Transit Oriented Development (TOD)-Mix Use",
      "isActive": 1,
      "edcPercentage": 25,
      "idwPercentage": 25,
      "plotTypeId": 2,
      "isDisableForNewEntry": 0,
      "disableRemarks": "Transit Oriented Development (TOD)-Mix Use Development",
      "scrutinyFeeCharges": "",
      "licenseFeeCharges": "",
      "externalDevelopmentCharges": "",
      "conversionCharges": "",
      "stateInfrastructureDevelopmentCharges": ""
    },
    {
      "purposeId": 94,
      "name": "Commercial Plotted Colony",
      "purposeCode": "CPL",
      "caseType_id": 1,
      "description": "Policy dt. 06.03.2018 (PF-110)",
      "isActive": 1,
      "edcPercentage": 25,
      "idwPercentage": 25,
      "plotTypeId": 1,
      "isDisableForNewEntry": 0,
      "disableRemarks": "",
      "scrutinyFeeCharges": {
        "Commercial Plotted": {
          "far": 1.50
        }
      },
      "licenseFeeCharges": {
        "Commercial Plotted": {
          "far": 1.50
        }      },
      "externalDevelopmentCharges": {
        "Commercial Plotted": {
          "far": 1.50
        }      },
      "conversionCharges": {
        "Commercial Plotted": {
          "far": 1.50
        }      },
      "stateInfrastructureDevelopmentCharges": {
        "Commercial Plotted": {
          "far": 1.50
        }      }
    },
    {
      "purposeId": 111,
      "name": "Sectoral Plan Pockets (SPRP)-GH",
      "purposeCode": "SPRP(RGH)",
      "caseType_id": 1,
      "description": "Sectoral Plan Pockets (SPRP)-GH",
      "isActive": 1,
      "edcPercentage": 25,
      "idwPercentage": 25,
      "plotTypeId": 2,
      "isDisableForNewEntry": 0,
      "disableRemarks": "",
      "scrutinyFeeCharges": {
        "Group Housing Commercial": {
          "far": 1.75
        }
      },
      "licenseFeeCharges": {
        "Group Housing Commercial": {
          "far": 1.50
        }      },
      "externalDevelopmentCharges": {
        "Group Housing Commercial": {
          "far": 1.50
        }      },
      "conversionCharges": {
        "Group Housing Commercial": {
          "far": 1.50
        }      },
      "stateInfrastructureDevelopmentCharges": {
        "Group Housing Commercial": {
          "far": 1.50
        }      }
    },
    {
      "purposeId": 112,
      "name": "Development of Retirement",
      "purposeCode": "DRH",
      "caseType_id": 1,
      "description": "Development of Retirement Housing",
      "isActive": 1,
      "edcPercentage": null,
      "idwPercentage": null,
      "plotTypeId": 1,
      "isDisableForNewEntry": 1,
      "disableRemarks": "",
      "scrutinyFeeCharges": "",
      "licenseFeeCharges": "",
      "externalDevelopmentCharges": "",
      "conversionCharges": "",
      "stateInfrastructureDevelopmentCharges": ""
    },
    {
      "purposeId": 113,
      "name": "Retirement Housing Project",
      "purposeCode": "RHP",
      "caseType_id": 1,
      "description": "Retirement Housing Project",
      "isActive": 1,
      "edcPercentage": null,
      "idwPercentage": null,
      "plotTypeId": 2,
      "isDisableForNewEntry": 1,
      "disableRemarks": "",
      "scrutinyFeeCharges": "",
      "licenseFeeCharges": "",
      "externalDevelopmentCharges": "",
      "conversionCharges": "",
      "stateInfrastructureDevelopmentCharges": ""
    }
  ]
}